win_maximize/__init__.py
win_maximize/__version__.py
win_maximize/parent_tree.py
win_maximize-1.0.2.dist-info/LICENSE
win_maximize-1.0.2.dist-info/METADATA
win_maximize-1.0.2.dist-info/WHEEL
win_maximize-1.0.2.dist-info/entry_points.txt
win_maximize-1.0.2.dist-info/top_level.txt
win_maximize-1.0.2.dist-info/RECORD
