Metadata-Version: 2.1
Name: win-maximize
Version: 1.0.2
Summary: Maximize window based on title, with selection of monitor
Home-page: https://github.com/alkuzad/win-maximize-python
Author: Dawid Gosławski
Author-email: dawid@dawidgoslawski.pl
License: MIT
Platform: UNKNOWN
Classifier: License :: OSI Approved :: MIT License
Classifier: Programming Language :: Python
Classifier: Programming Language :: Python :: 3
Classifier: Programming Language :: Python :: 3.6
Classifier: Programming Language :: Python :: Implementation :: CPython
Classifier: Programming Language :: Python :: Implementation :: PyPy
Requires-Python: >=3.7.0
Requires-Dist: pypiwin32 (==223)
